Metadata-Version: 2.4
Name: lca_algebraic_dev25
Version: 1.3.2
Summary: This library provides a layer above brightway2 for defining parametric models and running super fast LCA for monte carlo analysis.
Author-email: OIE - Mines ParisTech <raphael.jolivet@mines-paristech.fr>
License: BSD
Project-URL: Homepage, https://lca-algebraic.readthedocs.io/en/stable/
Project-URL: Repository, https://github.com/oie-mines-paristech/lca_algebraic.git
Project-URL: Documentation, https://lca-algebraic.readthedocs.io/
Project-URL: Changelog, https://github.com/oie-mines-paristech/lca_algebraic/blob/main/RELEASE_NOTES.md
Keywords: LCA,brightway2,monte-carlo,parametric
Classifier: License :: OSI Approved :: BSD License
Classifier: Programming Language :: Python :: 3.10
Classifier: Programming Language :: Python :: 3.11
Classifier: Programming Language :: Python :: 3.12
Requires-Python: <3.13,>=3.10
License-File: LICENSE
Requires-Dist: tabulate
Requires-Dist: ipywidgets
Requires-Dist: pandas
Requires-Dist: pyarrow
Requires-Dist: seaborn
Requires-Dist: sympy
Requires-Dist: matplotlib
Requires-Dist: deprecation
Requires-Dist: brightway2
Requires-Dist: SALib
Requires-Dist: pint
Requires-Dist: typing-extensions
Requires-Dist: pypardiso; platform_machine == "x86_64"
Dynamic: license-file
